pipeline2app/xnat/__init__.py
pipeline2app/xnat/_version.py
pipeline2app/xnat/command.py
pipeline2app/xnat/deploy.py
pipeline2app/xnat/image.py
pipeline2app/xnat/cli/__init__.py
pipeline2app/xnat/cli/base.py
pipeline2app/xnat/cli/deploy.py
pipeline2app/xnat/cli/entrypoint.py
pipeline2app/xnat/tests/test_app.py
pipeline2app/xnat/tests/test_cli_xnat_images.py
pipeline2app/xnat/tests/test_command.py
pipeline2app_xnat-0.7.1.dist-info/METADATA
pipeline2app_xnat-0.7.1.dist-info/WHEEL
pipeline2app_xnat-0.7.1.dist-info/licenses/LICENSE
pipeline2app_xnat-0.7.1.dist-info/RECORD
